namespaxe/__init__.py
namespaxe/cli.py
namespaxe-0.1.9.dist-info/METADATA
namespaxe-0.1.9.dist-info/WHEEL
namespaxe-0.1.9.dist-info/entry_points.txt
namespaxe-0.1.9.dist-info/top_level.txt
namespaxe-0.1.9.dist-info/RECORD
