Metadata-Version: 2.4
Name: namespaxe
Version: 0.1.9
Summary: A command-line tool for interacting with cloud services.
Home-page: https://github.com/pyincorporation-com/namespaxe-cli
Author: Gabriel Nzilantuzu
Author-email: gabrielnzilantuzu@pyincorporation.com
Classifier: Programming Language :: Python :: 3
Classifier: License :: OSI Approved :: MIT License
Classifier: Operating System :: OS Independent
Requires-Python: >=3.6
Requires-Dist: requests
Requires-Dist: click
Requires-Dist: pyyaml
Requires-Dist: tabulate
Dynamic: author
Dynamic: author-email
Dynamic: classifier
Dynamic: description
Dynamic: description-content-type
Dynamic: home-page
Dynamic: requires-dist
Dynamic: requires-python
Dynamic: summary
